mahnamahna/__init__.py
mahnamahna/readability.py
mahnamahna/voice/__init__.py
mahnamahna/voice/__main__.py
mahnamahna-0.0.2.dist-info/METADATA
mahnamahna-0.0.2.dist-info/entry_points.txt
mahnamahna-0.0.2.dist-info/WHEEL
mahnamahna-0.0.2.dist-info/RECORD
