Metadata-Version: 2.1
Name: mahnamahna
Version: 0.0.2
Summary: Media (text/audio/video) analysis and manipulation
Home-page: https://ragt.ag/code/projects/mahnamahna
License: AGPL-3.0-or-later
Author: Angelo Gladding
Author-email: angelo@ragt.ag
Requires-Python: >=3.10,<3.11
Classifier: License :: OSI Approved :: GNU Affero General Public License v3 or later (AGPLv3+)
Classifier: Programming Language :: Python :: 3
Classifier: Programming Language :: Python :: 3.10
Requires-Dist: gTTS (>=2.2.3,<3.0.0)
Requires-Dist: nltk (>=3.8.1,<4.0.0)
Requires-Dist: pyglet (>=2.0.10,<3.0.0)
Requires-Dist: pyttsx3 (>=2.90,<3.0)
Requires-Dist: sounddevice (>=0.4.4,<0.5.0)
Requires-Dist: vosk (>=0.3.32,<0.4.0)
Requires-Dist: webagt (>=0.2.3,<0.3.0)
Project-URL: Documentation, https://ragt.ag/code/projects/mahnamahna/api
Project-URL: Repository, https://ragt.ag/code/projects/mahnamahna.git
